mcp_email_server/__init__.py
mcp_email_server/app.py
mcp_email_server/cli.py
mcp_email_server/config.py
mcp_email_server/log.py
mcp_email_server/permissions.py
mcp_email_server/ui.py
mcp_email_server/emails/__init__.py
mcp_email_server/emails/classic.py
mcp_email_server/emails/dispatcher.py
mcp_email_server/emails/models.py
mcp_email_server/emails/provider/__init__.py
mcp_email_server/tools/__init__.py
mcp_email_server/tools/claude_desktop_config.json
mcp_email_server/tools/installer.py
up_mcp_email-0.1.0.dist-info/METADATA
up_mcp_email-0.1.0.dist-info/WHEEL
up_mcp_email-0.1.0.dist-info/entry_points.txt
up_mcp_email-0.1.0.dist-info/licenses/LICENSE
up_mcp_email-0.1.0.dist-info/RECORD
