Metadata-Version: 2.4
Name: up-mcp-email
Version: 0.1.0
Summary: ultraPRO Email MCP Server - IMAP and SMTP integration for Claude
Project-URL: Repository, https://github.com/cobach/up-mcp-email
Author-email: César Obach / ultraBASE <cesar@ultrabase.cl>
License-Expression: MIT
License-File: LICENSE
Keywords: Claude,IMAP,MCP,SMTP,email,ultraPRO
Classifier: Intended Audience :: Developers
Classifier: Programming Language :: Python
Classifier: Programming Language :: Python :: 3
Classifier: Programming Language :: Python :: 3.10
Classifier: Programming Language :: Python :: 3.11
Classifier: Programming Language :: Python :: 3.12
Classifier: Programming Language :: Python :: 3.13
Classifier: Programming Language :: Python :: 3.14
Classifier: Topic :: Software Development :: Libraries :: Python Modules
Requires-Python: <4.0,>=3.10
Requires-Dist: aioimaplib>=2.0.1
Requires-Dist: aiosmtplib>=4.0.0
Requires-Dist: gradio>=6.0.1
Requires-Dist: jinja2>=3.1.5
Requires-Dist: loguru>=0.7.3
Requires-Dist: markdown>=3.5.0
Requires-Dist: mcp[cli]>=1.3.0
Requires-Dist: pydantic-settings[toml]>=2.11.0
Requires-Dist: pydantic>=2.11.0
Requires-Dist: tomli-w>=1.2.0
Requires-Dist: typer>=0.15.1
